bittensor_wallet-3.1.0.dist-info/METADATA
bittensor_wallet-3.1.0.dist-info/WHEEL
bittensor_wallet-3.1.0.dist-info/licenses/LICENSE
bittensor_wallet/__init__.py
bittensor_wallet/__init__.pyi
bittensor_wallet/bittensor_wallet.cpython-311-darwin.so
bittensor_wallet/config/__init__.py
bittensor_wallet/config/__init__.pyi
bittensor_wallet/errors/__init__.py
bittensor_wallet/errors/__init__.pyi
bittensor_wallet/keyfile/__init__.py
bittensor_wallet/keyfile/__init__.pyi
bittensor_wallet/keypair/__init__.py
bittensor_wallet/keypair/__init__.pyi
bittensor_wallet/mock/__init__.py
bittensor_wallet/mock/keyfile_mock.py
bittensor_wallet/mock/wallet_mock.py
bittensor_wallet/py.typed
bittensor_wallet/utils/__init__.py
bittensor_wallet/utils/__init__.pyi
bittensor_wallet/wallet/__init__.py
bittensor_wallet/wallet/__init__.pyi
bittensor_wallet-3.1.0.dist-info/RECORD
